urlpath_filereader/__init__.py
urlpath_filereader-1.2.0.dist-info/METADATA
urlpath_filereader-1.2.0.dist-info/WHEEL
urlpath_filereader-1.2.0.dist-info/top_level.txt
urlpath_filereader-1.2.0.dist-info/RECORD
