Metadata-Version: 2.4
Name: urlpath-filereader
Version: 1.2.0
Summary: urlpath-filereader - библиотека для чтения файлов из локальной файловой системы и URL-адресов
Home-page: https://github.com/MagIlyasDOMA/urlpath-filereader
Author: Маг Ильяс DOMA (MagIlyasDOMA)
Author-email: magilyas.doma.09@list.ru
Classifier: Development Status :: 5 - Production/Stable
Classifier: Intended Audience :: Developers
Classifier: License :: OSI Approved :: MIT License
Classifier: Programming Language :: Python
Classifier: Programming Language :: Python :: 3
Classifier: Programming Language :: Python :: 3.10
Classifier: Programming Language :: Python :: 3.11
Classifier: Programming Language :: Python :: 3.12
Classifier: Programming Language :: Python :: 3.13
Classifier: Programming Language :: Python :: 3.14
Classifier: Operating System :: OS Independent
Classifier: Topic :: Software Development :: Libraries :: Python Modules
Classifier: Topic :: Utilities
Requires-Python: >=3.10
Requires-Dist: requests
Requires-Dist: chardet>=2.0.0
Requires-Dist: pathlike-typing
Dynamic: author
Dynamic: author-email
Dynamic: classifier
Dynamic: description
Dynamic: description-content-type
Dynamic: home-page
Dynamic: requires-dist
Dynamic: requires-python
Dynamic: summary
